neuralRaven/__init__.py
neuralRaven/core.cp311-win_amd64.pyd
neuralRaven/core.cp313-win_amd64.pyd
neuralRaven/core.cp39-win_amd64.pyd
neuralRaven/core.cpp
neuralRaven/core.pyx
neuralRaven/core_py.py
neuralRaven/env.py
neuralRaven/inputs.py
neuralRaven/io.py
neuralRaven/originalcode.py
neuralraven-1.0.0.dist-info/licenses/LICENSE
neuralraven-1.0.0.dist-info/METADATA
neuralraven-1.0.0.dist-info/WHEEL
neuralraven-1.0.0.dist-info/top_level.txt
neuralraven-1.0.0.dist-info/RECORD
