Metadata-Version: 2.4
Name: neuralRaven
Version: 1.0.0
Summary: Library of neural network with a evolutive algorithm of autolearned
Author-email: Carlos Gerardo Euresty Uribe <gerardo.eeuresty@itcelaya.edu.mx>, Jesus Miguel Cerda Gonzalez <cerda.gonzalez.jesus@gmail.com>
License: MIT
Requires-Python: >=3.8
License-File: LICENSE
Requires-Dist: numpy
Dynamic: license-file
